Metadata-Version: 2.1
Name: customChatbot
Version: 0.1.2
Summary: It is a custom GPT-3 bot that can be used to answer questions based on a custom dataset
Author: Me
